dimage/__init__.py
dimage/cli.py
dimage/config.py
dimage/downloader.py
dimage/extractor.py
dimage/filesystem.py
dimage-2025.7.7.dist-info/licenses/LICENSE
dimage-2025.7.7.dist-info/METADATA
dimage-2025.7.7.dist-info/WHEEL
dimage-2025.7.7.dist-info/entry_points.txt
dimage-2025.7.7.dist-info/top_level.txt
dimage-2025.7.7.dist-info/RECORD
