Metadata-Version: 2.4
Name: dimage
Version: 2025.7.7
Summary: Downloads all media assets from JSON files generated by DiscordChatExporter.
Author: Inc44
License-Expression: MIT
Project-URL: Repository, https://github.com/Inc44/Dimage.git
Project-URL: Issues, https://github.com/Inc44/Dimage/issues
Classifier: Operating System :: OS Independent
Classifier: Programming Language :: Python :: 3
Classifier: Programming Language :: Python :: 3.9
Classifier: Programming Language :: Python :: 3.10
Classifier: Programming Language :: Python :: 3.11
Classifier: Programming Language :: Python :: 3.12
Requires-Python: >=3.9
License-File: LICENSE
Requires-Dist: python-dateutil==2.9.0.post0
Requires-Dist: requests==2.32.4
Requires-Dist: tqdm==4.67.1
Dynamic: license-file
